{"license":"Apache 2.0","tarball_file_size":1044628,"version":"1.0.16","published_at":"2015-08-31T10:35:25Z","average_rating":null,"cookbook":"https://supermarket.chef.io/api/v1/cookbooks/docker","file":"https://supermarket.chef.io/api/v1/cookbooks/docker/versions/1.0.16/download","quality_metrics":[{"name":"Foodcritic","failed":true,"feedback":"FC005: Avoid repetition of resource declarations: /tmp/cook/bddc038a88dbf67c60928bfb/docker/libraries/provider_docker_service_systemd.rb:9\nFC031: Cookbook without metadata file: /tmp/cook/bddc038a88dbf67c60928bfb/docker/metadata.rb:1\nFC045: Consider setting cookbook name in metadata: /tmp/cook/bddc038a88dbf67c60928bfb/docker/metadata.rb:1"}],"supports":{"centos":">= 0.0.0","fedora":">= 0.0.0","debian":">= 0.0.0","ubuntu":">= 0.0.0","redhat":">= 0.0.0","amazon":">= 0.0.0"}}